instadb/__init__.py
instadb/connection.py
instadb/util.py
instadb-0.4.2.dist-info/DESCRIPTION.rst
instadb-0.4.2.dist-info/METADATA
instadb-0.4.2.dist-info/RECORD
instadb-0.4.2.dist-info/WHEEL
instadb-0.4.2.dist-info/metadata.json
instadb-0.4.2.dist-info/top_level.txt
