Metadata-Version: 2.0
Name: instadb
Version: 0.4.2
Summary: A simple and light DB package
Home-page: https://github.com/mathieuripert/instadb
Author: Mathieu Ripert
Author-email: mathieu@instacart.com
License: BSD
Platform: UNKNOWN
Requires-Dist: pandas
Requires-Dist: psycopg2
